<?xml version="1.0" encoding="UTF-8"?>

<Organization xmlns="http://hl7.org/fhir">
  <id value="DDCC-Organization-Arabic"/>
  <meta>
    <profile value="http://worldhealthorganization.github.io/ddcc/StructureDefinition/DDCCOrganization"/>
  </meta>
  <text>
    <status value="generated"/><div xmlns="http://www.w3.org/1999/xhtml"><p><b>Generated Narrative</b></p><p><b>name</b>: مستشفى حكومي</p></div>
  </text>
  <name value="&#x645;&#x633;&#x62A;&#x634;&#x641;&#x649; &#x62D;&#x643;&#x648;&#x645;&#x64A;"/>
</Organization>